sim2lbuilder/__init__.py
sim2lbuilder/_version.py
sim2lbuilder/components.py
sim2lbuilder/sim2lbuilder.py
sim2lbuilder/utils.py
sim2lbuilder/views.py
sim2lbuilder-0.0.7.dist-info/METADATA
sim2lbuilder-0.0.7.dist-info/WHEEL
sim2lbuilder-0.0.7.dist-info/top_level.txt
sim2lbuilder-0.0.7.dist-info/RECORD
