Metadata-Version: 2.1
Name: sim2lbuilder
Version: 0.0.7
Summary: Simtool builder
Home-page: https://github.com/denphi/sim2lbuilder
Author: nanoHUB
Author-email: denphi@denphi.com
License: BSD
Keywords: IPython
Platform: Linux
Platform: Mac OS X
Platform: Windows
Classifier: Intended Audience :: Developers
Classifier: Intended Audience :: Science/Research
Classifier: License :: OSI Approved :: BSD License
Classifier: Programming Language :: Python
Classifier: Programming Language :: Python :: 3
Classifier: Programming Language :: Python :: 3.4
Classifier: Programming Language :: Python :: 3.5
Classifier: Programming Language :: Python :: 3.6
Classifier: Framework :: Jupyter
Requires-Dist: ipywidgets (>=7.5.0)
Requires-Dist: simtool (>=0.3.3)
Requires-Dist: ipython (>=7.4.0)
Requires-Dist: traitlets (>=4.3.2)
Requires-Dist: ipysheet (>=0.4.1)
Requires-Dist: nanohub-uidl (>=0.1.5)
Requires-Dist: Pillow (>=7.2)
Provides-Extra: docs
Provides-Extra: examples
Provides-Extra: test
